decisionlab/__init__.py
decisionlab/decision_lab.py
decisionlab/team_requests.py
decisionlab-0.1.1.dist-info/METADATA
decisionlab-0.1.1.dist-info/WHEEL
decisionlab-0.1.1.dist-info/top_level.txt
decisionlab-0.1.1.dist-info/RECORD
