Metadata-Version: 2.1
Name: decisionlab
Version: 0.1.1
Summary: A Python package for accessing decision data from JustDecision.com
Home-page: https://github.com/TuDecides/decisionlab
Author: decisionLab
Author-email: jsanchezcastillejos@gmail.com
Classifier: Development Status :: 3 - Alpha
Classifier: Intended Audience :: Developers
Classifier: License :: OSI Approved :: MIT License
Classifier: Programming Language :: Python :: 3
Classifier: Programming Language :: Python :: 3.6
Classifier: Programming Language :: Python :: 3.7
Classifier: Programming Language :: Python :: 3.8
Classifier: Programming Language :: Python :: 3.9
